{
  "_comment": "Reproducible reconstruction manifest for refs/. fetch!=null => byte-reproducible from the pinned arXiv id (verified this session); fetch==null => content-addressed cache only ($AIPM_REFS_CACHE/<sha256>). Hashes are authoritative (== checksums.sha256). Regenerate-or-edit by hand; keep in sync with checksums.sha256.",
  "arxiv_verified": [
    "2405.02434",
    "2604.08380"
  ],
  "files": [
    {
      "path": "baak-moslehian/baak-moslehian-J-star-stability.pdf",
      "sha256": "027cffddd2735fbe71d889c31539b30095e7447486fd1e79e0d216f6ce9ff449",
      "source_id": "baak-moslehian",
      "fetch": null,
      "note": "journal/preprint PDF \u2014 source not pinned/verified"
    },
    {
      "path": "blecher-neal-1508.01530/blecher-neal-1508.01530.txt",
      "sha256": "06ca238eebee9ba772b8f72d72a7845e72b0da9ca7788a93cf89b58fc3b97ca1",
      "source_id": "blecher-neal-1508.01530",
      "fetch": null,
      "note": "bespoke text extraction (not an arXiv-native file)"
    },
    {
      "path": "blecher-neal-1905.05836/blecher-neal-1905.05836.txt",
      "sha256": "e7b34b75aa6578be41071a9dfeaae8cc316dc23282ca5b9d26d8d8fef6f89097",
      "source_id": "blecher-neal-1905.05836",
      "fetch": null,
      "note": "bespoke text extraction (not an arXiv-native file)"
    },
    {
      "path": "blecher-read-2019/contractive-projections-real-positive.tex",
      "sha256": "767b69596363d005196c366b37e7499c6428dd1d0820a2ac4c3f32cdf31fdf50",
      "source_id": "blecher-read-2019",
      "fetch": null,
      "note": "local .tex extraction (arXiv id/source not pinned/verified)"
    },
    {
      "path": "chu-russo-1512.03347/chu-russo-1512.03347.pdf",
      "sha256": "8597dc5556996e830fc2f404ceb0632810ce130c919e998c61971599f374e3cf",
      "source_id": "chu-russo-1512.03347",
      "fetch": null,
      "note": "recorded PDF predates current arXiv regeneration (no version hash-matches)"
    },
    {
      "path": "effros-stormer-1979/ocr-pages/page-01.png",
      "sha256": "2ad39ff5efae37b94107d615e834321ee9ccf8dddb6a1d85813e86da0d4f5e6a",
      "source_id": "effros-stormer-1979",
      "fetch": null,
      "note": "OCR page-scans + text of a 1979 Math. Scand. paper \u2014 bespoke, not reproducible by fetch"
    },
    {
      "path": "effros-stormer-1979/ocr-pages/page-01.txt",
      "sha256": "b5594fe97fdafae144b70eecef1fcf79cdb7b68a06ee8ef8b03a7b5f9b65cf49",
      "source_id": "effros-stormer-1979",
      "fetch": null,
      "note": "OCR page-scans + text of a 1979 Math. Scand. paper \u2014 bespoke, not reproducible by fetch"
    },
    {
      "path": "effros-stormer-1979/ocr-pages/page-02.png",
      "sha256": "69d19c463b6b845301f6abe40a8fd0bad8de768c37a2bded5065e2281176bf2c",
      "source_id": "effros-stormer-1979",
      "fetch": null,
      "note": "OCR page-scans + text of a 1979 Math. Scand. paper \u2014 bespoke, not reproducible by fetch"
    },
    {
      "path": "effros-stormer-1979/ocr-pages/page-02.txt",
      "sha256": "5d8290904cbbef072ca6c33a42f94c8b94c99987ad2820d1682b112873366ce7",
      "source_id": "effros-stormer-1979",
      "fetch": null,
      "note": "OCR page-scans + text of a 1979 Math. Scand. paper \u2014 bespoke, not reproducible by fetch"
    },
    {
      "path": "effros-stormer-1979/ocr-pages/page-03.png",
      "sha256": "c74b515c662f9bb5f069f2e642c0554e1ea5d5e67c24a2b36b96828f3f12c225",
      "source_id": "effros-stormer-1979",
      "fetch": null,
      "note": "OCR page-scans + text of a 1979 Math. Scand. paper \u2014 bespoke, not reproducible by fetch"
    },
    {
      "path": "effros-stormer-1979/ocr-pages/page-03.txt",
      "sha256": "de9c217ecc0b729f165461e1eb24960ffbf7acba9599fed120badd45de7f48c6",
      "source_id": "effros-stormer-1979",
      "fetch": null,
      "note": "OCR page-scans + text of a 1979 Math. Scand. paper \u2014 bespoke, not reproducible by fetch"
    },
    {
      "path": "effros-stormer-1979/ocr-pages/page-04.png",
      "sha256": "f6264ec83f8458f73e06a62fdde232bb633032eab42e118b22157b7dd86251c5",
      "source_id": "effros-stormer-1979",
      "fetch": null,
      "note": "OCR page-scans + text of a 1979 Math. Scand. paper \u2014 bespoke, not reproducible by fetch"
    },
    {
      "path": "effros-stormer-1979/ocr-pages/page-04.txt",
      "sha256": "833b01de6e6f02b037c35a8340711a62bc2f18af8b31afa30afba2f0248b5608",
      "source_id": "effros-stormer-1979",
      "fetch": null,
      "note": "OCR page-scans + text of a 1979 Math. Scand. paper \u2014 bespoke, not reproducible by fetch"
    },
    {
      "path": "effros-stormer-1979/ocr-pages/page-05.png",
      "sha256": "d0e991e98864f218484db9380b62c1bd3ee4d86f3440ae04815b7112c54358ad",
      "source_id": "effros-stormer-1979",
      "fetch": null,
      "note": "OCR page-scans + text of a 1979 Math. Scand. paper \u2014 bespoke, not reproducible by fetch"
    },
    {
      "path": "effros-stormer-1979/ocr-pages/page-05.txt",
      "sha256": "80ae5aacf9ce018c4c18709a4bd8a6c44d8cd99cd23842f1a8a93f4442e2975b",
      "source_id": "effros-stormer-1979",
      "fetch": null,
      "note": "OCR page-scans + text of a 1979 Math. Scand. paper \u2014 bespoke, not reproducible by fetch"
    },
    {
      "path": "effros-stormer-1979/ocr-pages/page-06.png",
      "sha256": "14c32f3a15bcd6af78b2324fbc48216f5425055b961841cb7fe5037683d36151",
      "source_id": "effros-stormer-1979",
      "fetch": null,
      "note": "OCR page-scans + text of a 1979 Math. Scand. paper \u2014 bespoke, not reproducible by fetch"
    },
    {
      "path": "effros-stormer-1979/ocr-pages/page-06.txt",
      "sha256": "687a8024feb5ceacb0d22150fbaaa4e505c619383697903539f8c78c02fd45cd",
      "source_id": "effros-stormer-1979",
      "fetch": null,
      "note": "OCR page-scans + text of a 1979 Math. Scand. paper \u2014 bespoke, not reproducible by fetch"
    },
    {
      "path": "effros-stormer-1979/ocr-pages/page-07.png",
      "sha256": "699c82d777417a87f7deea360caa8c1b5796f357e73745adfb6a58417988fe2b",
      "source_id": "effros-stormer-1979",
      "fetch": null,
      "note": "OCR page-scans + text of a 1979 Math. Scand. paper \u2014 bespoke, not reproducible by fetch"
    },
    {
      "path": "effros-stormer-1979/ocr-pages/page-07.txt",
      "sha256": "606847efe808170a42f9718a95895824f002c349d2cda37770e7638427fb0323",
      "source_id": "effros-stormer-1979",
      "fetch": null,
      "note": "OCR page-scans + text of a 1979 Math. Scand. paper \u2014 bespoke, not reproducible by fetch"
    },
    {
      "path": "effros-stormer-1979/ocr-pages/page-08.png",
      "sha256": "f2733ec86101bb8243cf55896100a7e4524f3f29e4052cc5e2201ea7bb963309",
      "source_id": "effros-stormer-1979",
      "fetch": null,
      "note": "OCR page-scans + text of a 1979 Math. Scand. paper \u2014 bespoke, not reproducible by fetch"
    },
    {
      "path": "effros-stormer-1979/ocr-pages/page-08.txt",
      "sha256": "d91e61f22ec42832f9fcef43719e670cda36c2cb9348483ec7810a3415c7d756",
      "source_id": "effros-stormer-1979",
      "fetch": null,
      "note": "OCR page-scans + text of a 1979 Math. Scand. paper \u2014 bespoke, not reproducible by fetch"
    },
    {
      "path": "effros-stormer-1979/ocr-pages/page-09.png",
      "sha256": "3929e60f156bb1ddc7c51d1d2be1e9e402c3e80e60ba152c52b164e9e3ad9974",
      "source_id": "effros-stormer-1979",
      "fetch": null,
      "note": "OCR page-scans + text of a 1979 Math. Scand. paper \u2014 bespoke, not reproducible by fetch"
    },
    {
      "path": "effros-stormer-1979/ocr-pages/page-09.txt",
      "sha256": "c209e65caa9f8e0f900218001fae423edbde0915105e7e050b4d1de87466eb32",
      "source_id": "effros-stormer-1979",
      "fetch": null,
      "note": "OCR page-scans + text of a 1979 Math. Scand. paper \u2014 bespoke, not reproducible by fetch"
    },
    {
      "path": "effros-stormer-1979/ocr-pages/page-10.png",
      "sha256": "c9992e71c7f2120543c0177fa8eb01f5b0b738a083c6d81da4b348e3569f7a13",
      "source_id": "effros-stormer-1979",
      "fetch": null,
      "note": "OCR page-scans + text of a 1979 Math. Scand. paper \u2014 bespoke, not reproducible by fetch"
    },
    {
      "path": "effros-stormer-1979/ocr-pages/page-10.txt",
      "sha256": "c30f4310eba5809f54f2fa798f39677505c2fb5116235c13aa3ee699d201e759",
      "source_id": "effros-stormer-1979",
      "fetch": null,
      "note": "OCR page-scans + text of a 1979 Math. Scand. paper \u2014 bespoke, not reproducible by fetch"
    },
    {
      "path": "effros-stormer-1979/ocr-pages/page-11.png",
      "sha256": "99eacd3e7d589bb03e7b88a4d4b0b15368abbfe4812515b7ef3c46ac2e260f96",
      "source_id": "effros-stormer-1979",
      "fetch": null,
      "note": "OCR page-scans + text of a 1979 Math. Scand. paper \u2014 bespoke, not reproducible by fetch"
    },
    {
      "path": "effros-stormer-1979/ocr-pages/page-11.txt",
      "sha256": "a424e2faa5e93fe14140b33befec6bfe68c1d22d8ed2a1f5e922ed1bf277494e",
      "source_id": "effros-stormer-1979",
      "fetch": null,
      "note": "OCR page-scans + text of a 1979 Math. Scand. paper \u2014 bespoke, not reproducible by fetch"
    },
    {
      "path": "effros-stormer-1979/ocr-pages/page-12.png",
      "sha256": "24ea4891e8cd6c7f04aab2114ea30733c3f20d25a4ee22052cc4eec444e57e3c",
      "source_id": "effros-stormer-1979",
      "fetch": null,
      "note": "OCR page-scans + text of a 1979 Math. Scand. paper \u2014 bespoke, not reproducible by fetch"
    },
    {
      "path": "effros-stormer-1979/ocr-pages/page-12.txt",
      "sha256": "958b1ec7eedd3247677e2968969070b34a39dd532147333de5d1d232441003f7",
      "source_id": "effros-stormer-1979",
      "fetch": null,
      "note": "OCR page-scans + text of a 1979 Math. Scand. paper \u2014 bespoke, not reproducible by fetch"
    },
    {
      "path": "effros-stormer-1979/positive-projections-jordan-structure.pdf",
      "sha256": "9718c140a2732c18272cf399d671175da46097573e5c44a378184d72e4683e2b",
      "source_id": "effros-stormer-1979",
      "fetch": null,
      "note": "OCR page-scans + text of a 1979 Math. Scand. paper \u2014 bespoke, not reproducible by fetch"
    },
    {
      "path": "effros-stormer-1979/positive-projections-jordan-structure.txt",
      "sha256": "ee3e9571f483c678ab4ec83579e8bef9c1399e8d319a66a073e1d60491f85468",
      "source_id": "effros-stormer-1979",
      "fetch": null,
      "note": "OCR page-scans + text of a 1979 Math. Scand. paper \u2014 bespoke, not reproducible by fetch"
    },
    {
      "path": "hos/hos-book.pdf",
      "sha256": "0222fcdad57448d0a5e5db90db2307bef47cdf28f93062721500efe78da20457",
      "source_id": "hos",
      "fetch": null,
      "note": "OCR of copyrighted Hanche-Olsen\u2013St\u00f8rmer (Pitman 1984) book \u2014 no public reproducible source"
    },
    {
      "path": "hos/joa-m.md",
      "sha256": "28740e73d547dd46919f74294739e8e0fa7f93b277419a13b29fdb22896b4e56",
      "source_id": "hos",
      "fetch": null,
      "note": "OCR of copyrighted Hanche-Olsen\u2013St\u00f8rmer (Pitman 1984) book \u2014 no public reproducible source"
    },
    {
      "path": "idel-2013/idel-2013.md",
      "sha256": "737cd6d3d82ae588a3fc4ac44bd3aa2ffa232f1bfa5c826d14f84dba45dbddc5",
      "source_id": "idel-2013",
      "fetch": null,
      "note": "OCR/markdown of a 2013 TUM thesis \u2014 bespoke conversion"
    },
    {
      "path": "itoh-1991/itoh-positive-projections-tokyo1991.txt",
      "sha256": "03bd2d3d6ebb28218afe9226fd151f912dc0502b07c2ad58c1f3d74f21b2f938",
      "source_id": "itoh-1991",
      "fetch": null,
      "note": "text extraction of a 1991 Tokyo J. Math. paper \u2014 no reproducible public source"
    },
    {
      "path": "kaup-1984/contractive-projections-jordan-cstar.pdf",
      "sha256": "16c72dafd7e16a862987dbb76fba88d669695390aa5a78494be2b55b1cb08dab",
      "source_id": "kaup-1984",
      "fetch": null,
      "note": "journal PDF (1984) \u2014 no reproducible public source"
    },
    {
      "path": "kitaev-2405.02434/approximate_algebras.tex",
      "sha256": "e7eb512a2ec2438d139c581fe48c017a6ffdc87c37f6fa7492159b757a9a9acb",
      "source_id": "kitaev-2405.02434",
      "fetch": {
        "kind": "arxiv-eprint-member",
        "id": "2405.02434"
      }
    },
    {
      "path": "kitaev-2405.02434/kitaev-2405.02434.pdf",
      "sha256": "a640ede701cd88308f1703c625e56b6a0cce28570813da77f473e6f5bc5106be",
      "source_id": "kitaev-2405.02434",
      "fetch": {
        "kind": "arxiv-pdf",
        "id": "2405.02434"
      }
    },
    {
      "path": "kitaev-2405.02434/kitaev-src.tar.gz",
      "sha256": "aed5b4c9ba0d62143ad5db70c3210fe35dfac3f6cc8021b6125ad1da4040c38c",
      "source_id": "kitaev-2405.02434",
      "fetch": {
        "kind": "arxiv-eprint",
        "id": "2405.02434"
      }
    },
    {
      "path": "kitaev-2405.02434/mypaths.sty",
      "sha256": "78887164f0d0453e01c4c5c3533f63c20c5ba19a7bcf4841e560215f0b03bb77",
      "source_id": "kitaev-2405.02434",
      "fetch": {
        "kind": "arxiv-eprint-member",
        "id": "2405.02434"
      }
    },
    {
      "path": "kitaev-2405.02434/mythm.sty",
      "sha256": "6eba432617eebf76865712ec04da9fb358c50747fbc0e414c6f90e9cb3136f0c",
      "source_id": "kitaev-2405.02434",
      "fetch": {
        "kind": "arxiv-eprint-member",
        "id": "2405.02434"
      }
    },
    {
      "path": "kitaev-2405.02434/myutil.sty",
      "sha256": "b2921f410c7ff040658500a0af48f7fea11561ffc5fff2335d42e76ca706b163",
      "source_id": "kitaev-2405.02434",
      "fetch": {
        "kind": "arxiv-eprint-member",
        "id": "2405.02434"
      }
    },
    {
      "path": "kitaev-2405.02434/two_holes-1.pdf",
      "sha256": "56d265e0b3c5321437699cb04f29eadf04a63afdff76fc3710fd8afe27f88048",
      "source_id": "kitaev-2405.02434",
      "fetch": {
        "kind": "arxiv-eprint-member",
        "id": "2405.02434"
      }
    },
    {
      "path": "kitaev-2405.02434/two_holes-2.pdf",
      "sha256": "62f550abb0aa7274f502c3e39e9d8be975df62156366eaca41cc170936a3e777",
      "source_id": "kitaev-2405.02434",
      "fetch": {
        "kind": "arxiv-eprint-member",
        "id": "2405.02434"
      }
    },
    {
      "path": "vlw-2604.08380/00README.json",
      "sha256": "d40dd491fbb511a7521131bc70846e314509101155f62edbccce8518d7de1bbb",
      "source_id": "vlw-2604.08380",
      "fetch": {
        "kind": "arxiv-eprint-member",
        "id": "2604.08380"
      }
    },
    {
      "path": "vlw-2604.08380/paper.bbl",
      "sha256": "a02ec430b6bcd4b415b49dfad561e3ca7491e403cd62fc7e4590a7a91208cdbc",
      "source_id": "vlw-2604.08380",
      "fetch": {
        "kind": "arxiv-eprint-member",
        "id": "2604.08380"
      }
    },
    {
      "path": "vlw-2604.08380/paper.tex",
      "sha256": "3395946df12f6606b2dd9b642dd13c055a5657a12f99d8335e5553473c071439",
      "source_id": "vlw-2604.08380",
      "fetch": {
        "kind": "arxiv-eprint-member",
        "id": "2604.08380"
      }
    },
    {
      "path": "vlw-2604.08380/positive-maps-2604.08380v2.pdf",
      "sha256": "674c92389c555732605030dd9f98e89c4684e994a03b3d99b5cb17c29fdf25f5",
      "source_id": "vlw-2604.08380",
      "fetch": {
        "kind": "arxiv-pdf",
        "id": "2604.08380"
      }
    },
    {
      "path": "vlw-2604.08380/preamble.tex",
      "sha256": "86d0b811ff0b97591a7ace8f3fc099fce2b4e3f17fe89865ef6593c43e34bb11",
      "source_id": "vlw-2604.08380",
      "fetch": {
        "kind": "arxiv-eprint-member",
        "id": "2604.08380"
      }
    },
    {
      "path": "vlw-2604.08380/vlw-src.tar.gz",
      "sha256": "2b4fc88195dac8cbeda3e1a449dc01b014c3d8dd59e1543950d63f3cde693316",
      "source_id": "vlw-2604.08380",
      "fetch": {
        "kind": "arxiv-eprint",
        "id": "2604.08380"
      }
    }
  ]
}
