{"type":"node_created","timestamp":"2026-06-07T14:18:25.360826843Z","node":{"id":"1.4.1","type":"claim","statement":"Tr(rho_omega x) \u003e= lambda Tr(x) for x\u003e=0. By GT-hyp rho_omega\u003e=lambda1, so rho_omega-lambda1\u003e=0 (GT-orderunit-def). By GT-trace-psd (self-duality of the positive cone of L(H): a in J^+ iff tr(ab)\u003e=0 for all b in J^+), with a:=rho_omega-lambda1\u003e=0 and b:=x\u003e=0, Tr((rho_omega-lambda1)x)\u003e=0, i.e. Tr(rho_omega x) \u003e= lambda Tr(x).","inference":"assumption","workflow_state":"available","epistemic_state":"pending","taint_state":"unresolved","content_hash":"980447f70f0afebe31c5fcd5e75371288c47d7cda70ea53f9f26252a91b1b4be","created":"2026-06-07T14:18:25.360811003Z","claimed_at":"0001-01-01T00:00:00Z"}}