{"type":"challenge_raised","timestamp":"2026-06-05T20:29:25.250269299Z","challenge_id":"ch-50c647e417cd8037","node_id":"1.5","target":"gap","reason":"The step ||P|| \u003c= ||Phi||+delta uses the triangle inequality ||Phi+(P-Phi)|| \u003c= ||Phi||+||P-Phi|| for the operator norm on End(B(H)_sa). PROJECT RULE: no standard facts. No refs/ source states the triangle inequality for the order-unit-norm-induced operator norm on End(B(H)_sa). HOS at the order-unit-norm locus (refs/hos/joa-m.md:368-372) only gives the order norm on the underlying space A, not the induced operator norm on its endomorphisms. Unprovenanced load-bearing fact.","severity":"major","raised_by":""}