{"type":"node_amended","timestamp":"2026-06-05T20:52:12.784332272Z","node_id":"1.4","previous_statement":"P(I)=I. By GT-positive-unital Phi(I)=I, so S(I)=(2Phi-I)(I)=I, hence S^2(I)=I and U(I)=(S^2-I)(I)=0. By GT-funcalc, R=f(S^2)=sum_{n\u003e=0} a_n U^n with constant term a_0=f(x0)=f(1)=1^(-1/2)=1 (value of f at the Taylor center). Since U(I)=0, U^n(I)=0 for all n\u003e=1, so R(I)=a_0 I=I; thus sgn(S)(I)=S R(I)=S(I)=I and P(I)=(I+sgn(S))(I)/2=I. Uses node 1.2.","new_statement":"P(I)=I. Phi(I)=I by hypothesis (def positive-unital-map). With S=2Phi-I (node 1.1), S(I)=I, so S^2(I)=I and U(I)=(S^2-I)(I)=0. By GT-funcalc, R=f(S^2)=sum_{n\u003e=0} a_n U^n with constant term a_0=f(x0)=f(1)=1. Since U(I)=0, U^n(I)=0 for n\u003e=1, so R(I)=a_0 I=I; thus sgn(S)(I)=S R(I)=S(I)=I, and P=(I+sgn(S))/2 (node 1.3) gives P(I)=(I+sgn(S))(I)/2=I. Uses nodes 1.1, 1.2, 1.3.","owner":"agent-A"}